friendli/__init__.py
friendli/auth.py
friendli/cli/__init__.py
friendli/cli/api/__init__.py
friendli/cli/api/chat_completions.py
friendli/cli/api/completions.py
friendli/cli/endpoint.py
friendli/cli/login.py
friendli/cli/main.py
friendli/cli/model.py
friendli/cli/project.py
friendli/cli/team.py
friendli/client/__init__.py
friendli/client/graphql/__init__.py
friendli/client/graphql/base.py
friendli/client/graphql/endpoint.py
friendli/client/graphql/model.py
friendli/client/graphql/team.py
friendli/client/graphql/user.py
friendli/client/http/__init__.py
friendli/client/http/base.py
friendli/client/http/login.py
friendli/context.py
friendli/di/__init__.py
friendli/di/injector.py
friendli/di/modules.py
friendli/enums.py
friendli/errors.py
friendli/formatter.py
friendli/logging.py
friendli/py.typed
friendli/schema/__init__.py
friendli/schema/api/__init__.py
friendli/schema/api/v1/__init__.py
friendli/schema/api/v1/chat/__init__.py
friendli/schema/api/v1/chat/completion_chunk.py
friendli/schema/api/v1/chat/completions.py
friendli/schema/api/v1/codegen/__init__.py
friendli/schema/api/v1/codegen/chat_completions_pb2.py
friendli/schema/api/v1/codegen/chat_completions_pb2.pyi
friendli/schema/api/v1/codegen/completions_pb2.py
friendli/schema/api/v1/codegen/completions_pb2.pyi
friendli/schema/api/v1/codegen/completions_pb2_grpc.py
friendli/schema/api/v1/codegen/response_format_pb2.py
friendli/schema/api/v1/codegen/response_format_pb2.pyi
friendli/schema/api/v1/codegen/text_to_image_pb2.py
friendli/schema/api/v1/codegen/text_to_image_pb2.pyi
friendli/schema/api/v1/completions.py
friendli/schema/api/v1/images/__init__.py
friendli/schema/api/v1/images/image.py
friendli/schema/config/__init__.py
friendli/schema/config/endpoint.py
friendli/schema/resource/__init__.py
friendli/schema/resource/v1/__init__.py
friendli/schema/resource/v1/attributes.py
friendli/schema/resource/v1/common.py
friendli/schema/resource/v1/endpoint.py
friendli/schema/resource/v1/model.py
friendli_client-1.5.8.dist-info/LICENSE
friendli_client-1.5.8.dist-info/METADATA
friendli_client-1.5.8.dist-info/WHEEL
friendli_client-1.5.8.dist-info/entry_points.txt
friendli_client-1.5.8.dist-info/RECORD
