Metadata-Version: 2.1
Name: friendli-client
Version: 1.5.8
Summary: Client of Friendli Suite.
Home-page: https://friendli.ai/
License: Apache-2.0
Keywords: generative-ai,serving,llm,inference,finetuning
Author: FriendliAI teams
Author-email: eng@friendli.ai
Requires-Python: >=3.8.1,<4.0.0
Classifier: License :: OSI Approved :: Apache Software License
Classifier: Programming Language :: Python :: 3
Classifier: Programming Language :: Python :: 3.9
Classifier: Programming Language :: Python :: 3.10
Classifier: Programming Language :: Python :: 3.11
Classifier: Programming Language :: Python :: 3.12
Classifier: Programming Language :: Python :: 3.13
Requires-Dist: PyYaml (>=6.0.1,<7.0.0)
Requires-Dist: fastapi (>=0.115.2,<0.116.0)
Requires-Dist: gql (>=3.4.1,<4.0.0)
Requires-Dist: grpc-stubs (>=1.53.0.5,<2.0.0.0)
Requires-Dist: grpcio (>=1.64.1,<2.0.0)
Requires-Dist: grpcio-tools (>=1.64.1,<2.0.0)
Requires-Dist: httpx (>=0.24.1,<0.25.0)
Requires-Dist: injector (>=0.21.0,<0.22.0)
Requires-Dist: jsonschema (>=4.17.3,<5.0.0)
Requires-Dist: protobuf (>=5.26.1,<6.0.0)
Requires-Dist: pydantic[email] (>=1.9.0,<3)
Requires-Dist: requests (>=2.32.0,<3.0.0)
Requires-Dist: rich (>=12.2.0,<13.0.0)
Requires-Dist: tqdm (>=4.66.3,<5.0.0)
Requires-Dist: typer (>=0.9.0,<0.10.0)
Requires-Dist: types-protobuf (>=5.26.0.20240422,<6.0.0.0)
Requires-Dist: uvicorn (>=0.23.2,<0.24.0)
Project-URL: Documentation, https://friendli.ai/docs/
Project-URL: Repository, https://github.com/friendliai/friendli-client
